Metadata-Version: 2.4
Name: siren-ai
Version: 0.1.2
Summary: Python SDK for the Siren Notification Platform.
License: MIT License
Project-URL: Homepage, https://github.com/KeyValueSoftwareSystems/siren-py-sdk
Project-URL: Documentation, https://github.com/KeyValueSoftwareSystems/siren-py-sdk#readme
Project-URL: Repository, https://github.com/KeyValueSoftwareSystems/siren-py-sdk
Project-URL: Bug Tracker, https://github.com/KeyValueSoftwareSystems/siren-py-sdk/issues
Keywords: siren,notifications,api,sdk,ai,messaging,communication
Classifier: Development Status :: 3 - Alpha
Classifier: Intended Audience :: Developers
Classifier: License :: OSI Approved :: MIT License
Classifier: Operating System :: OS Independent
Classifier: Programming Language :: Python :: 3
Classifier: Programming Language :: Python :: 3.8
Classifier: Programming Language :: Python :: 3.9
Classifier: Programming Language :: Python :: 3.10
Classifier: Programming Language :: Python :: 3.11
Classifier: Programming Language :: Python :: 3.12
Classifier: Topic :: Communications
Classifier: Topic :: Software Development :: Libraries :: Python Modules
Requires-Python: >=3.8
License-File: LICENSE
Requires-Dist: requests>=2.25.0
Requires-Dist: httpx>=0.26.0
Requires-Dist: pydantic[email]<3.0,>=2.0
Provides-Extra: dev
Requires-Dist: pytest>=7.0; extra == "dev"
Requires-Dist: pytest-cov; extra == "dev"
Requires-Dist: pytest-mock; extra == "dev"
Requires-Dist: requests-mock; extra == "dev"
Requires-Dist: pytest-asyncio>=0.20; extra == "dev"
Requires-Dist: respx<0.23,>=0.21.0; extra == "dev"
Requires-Dist: ruff; extra == "dev"
Requires-Dist: pyright; extra == "dev"
Requires-Dist: pre-commit; extra == "dev"
Requires-Dist: uv; extra == "dev"
Requires-Dist: python-dotenv; extra == "dev"
Requires-Dist: build>=0.10.0; extra == "dev"
Requires-Dist: twine>=3.8.0; extra == "dev"
Dynamic: license-file
